quartet_vrs/__init__.py
quartet_vrs/admin.py
quartet_vrs/apps.py
quartet_vrs/models.py
quartet_vrs/serializers.py
quartet_vrs/settings.py
quartet_vrs/urls.py
quartet_vrs/verification.py
quartet_vrs/views.py
quartet_vrs/wsgi.py
quartet_vrs/management/__init__.py
quartet_vrs/management/commands/__init__.py
quartet_vrs/management/commands/create_vrs_data.py
quartet_vrs/management/commands/create_vrs_groups.py
quartet_vrs/migrations/0001_initial.py
quartet_vrs/migrations/0002_delete_vrsgs1locations.py
quartet_vrs/migrations/0003_gtinmap.py
quartet_vrs/migrations/0004_requestlog.py
quartet_vrs/migrations/0005_auto_20200203_1514.py
quartet_vrs/migrations/0006_auto_20200203_1536.py
quartet_vrs/migrations/0007_auto_20200203_1545.py
quartet_vrs/migrations/0008_auto_20200203_1727.py
quartet_vrs/migrations/0009_auto_20200203_1728.py
quartet_vrs/migrations/0010_auto_20200204_1310.py
quartet_vrs/migrations/0011_auto_20200204_1430.py
quartet_vrs/migrations/0012_auto_20200204_1508.py
quartet_vrs/migrations/0013_auto_20200730_2121.py
quartet_vrs/migrations/0014_auto_20200730_2129.py
quartet_vrs/migrations/__init__.py
quartet_vrs-2.0.1.dist-info/AUTHORS.rst
quartet_vrs-2.0.1.dist-info/LICENSE
quartet_vrs-2.0.1.dist-info/METADATA
quartet_vrs-2.0.1.dist-info/WHEEL
quartet_vrs-2.0.1.dist-info/top_level.txt
quartet_vrs-2.0.1.dist-info/RECORD
