Metadata-Version: 2.1
Name: quartet-vrs
Version: 2.0.1
Summary: A GS1-compliant VRS interface for the open-source EPCIS QU4RTET platform.
Home-page: https://gitlab.com/serial-lab/quartet_vrs
Author: SerialLab
Author-email: slab@serial-lab.com
License: GPLv3
Keywords: quartet_vrs
Platform: UNKNOWN
Classifier: Development Status :: 5 - Production/Stable
Classifier: Intended Audience :: Healthcare Industry
Classifier: Intended Audience :: Manufacturing
Classifier: Intended Audience :: Developers
Classifier: License :: OSI Approved :: GNU Affero General Public License v3 or later (AGPLv3+)
Classifier: Natural Language :: English
Classifier: Programming Language :: Python :: 3
Classifier: Programming Language :: Python :: 3.5
Classifier: Programming Language :: Python :: 3.6
Requires-Dist: quartet-capture
Requires-Dist: quartet-masterdata
Requires-Dist: quartet-epcis
Requires-Dist: mixer
